legoman/__init__.py
legoman/legoman.py
legoman/legoman_cgi
legoman/demo/Makefile
legoman/demo/content/codehilite.css
legoman/demo/content/index.j2
legoman/demo/content/man.svg
legoman/demo/content/styles.css
legoman/demo/content/projects/bar_proj/index.md
legoman/demo/content/projects/foo_proj/cheetos_small.png
legoman/demo/content/projects/foo_proj/index.md
legoman/demo/content/projects/foo_proj/test.py
legoman/demo/templates/base.j2
legoman/demo/templates/default.j2
legoman/demo/templates/project.j2
legoman-3.0.5.data/scripts/legoman_cgi
legoman-3.0.5.dist-info/METADATA
legoman-3.0.5.dist-info/WHEEL
legoman-3.0.5.dist-info/entry_points.txt
legoman-3.0.5.dist-info/top_level.txt
legoman-3.0.5.dist-info/RECORD
