Metadata-Version: 2.1
Name: legoman
Version: 3.0.5
Summary: a tiny static website generator
Home-page: https://github.com/evidlo/legoman
Author: Evan Widloski
Author-email: evan@evanw.org
License: GPLv3
Keywords: static web generator jinja2 markdown
Platform: UNKNOWN
Classifier: Programming Language :: Python :: 3
